LICENSE
MANIFEST.in
README.md
setup.py
aliyun_computenest/__init__.py
aliyun_computenest/base.html
aliyun_computenest/main.html
aliyun_computenest/mkdocs_theme.yml
aliyun_computenest/css/theme.css
aliyun_computenest/img/favicon.ico
aliyun_computenest/img/logo-2x.png
aliyun_computenest/img/logo-bg.jpeg
aliyun_computenest/img/logo.png
aliyun_computenest/js/highlight.min.js
aliyun_computenest/js/theme.js
mkdocs_aliyun_computenest.egg-info/PKG-INFO
mkdocs_aliyun_computenest.egg-info/SOURCES.txt
mkdocs_aliyun_computenest.egg-info/dependency_links.txt
mkdocs_aliyun_computenest.egg-info/entry_points.txt
mkdocs_aliyun_computenest.egg-info/not-zip-safe
mkdocs_aliyun_computenest.egg-info/top_level.txt