Metadata-Version: 1.0
Name: mkdocs-aliyun-computenest
Version: 0.0.6
Summary: Aliyun computenest theme for MkDocs
Home-page: https://github.com/aliyun-computenest/quickstart-demo
Author: liuqi.lq
Author-email: liuqi.lq@alibaba-inc.com
License: BSD
Platform: UNKNOWN
